exponema/__init__.py
exponema/expon.py
exponema-0.0.1.dist-info/LICENSE
exponema-0.0.1.dist-info/METADATA
exponema-0.0.1.dist-info/WHEEL
exponema-0.0.1.dist-info/top_level.txt
exponema-0.0.1.dist-info/RECORD
