Metadata-Version: 2.1
Name: exponema
Version: 0.0.1
Summary: This package finds the exponent of a value with respect to a given degree
Home-page: https://www.RAINigeria.com
Author: Stephen Ogunmuyiwa
Author-email: ogunmuyiwatomiwo.official@gmail.com
Classifier: Programming Language :: Python :: 3
Classifier: License :: OSI Approved :: MIT License
Classifier: Operating System :: OS Independent
Requires-Python: >=3.7
License-File: LICENSE
